{"total_trip": {"total": {"141": {"taxi": 392}, "170": {"taxi": 389}, "186": {"taxi": 299}, "236": {"taxi": 967}, "237": {"taxi": 1035}}, "reb": {"141": {"taxi": 7}, "170": {"taxi": 22}, "186": {"taxi": 7}, "236": {"taxi": 16}, "237": {"taxi": 0}}}, "total_tripdist": {"total": {"taxi": 3928404.3172476813}, "reb": {"taxi": 73424.59724876974}}, "total_triptime": {"total": {"taxi": 877244}, "reb": {"taxi": 16399}}, "total_arrival": {"total": {"141": 1115, "170": 367, "186": 546, "236": 1620, "237": 1634}, "served": {"141": 366, "170": 446, "186": 279, "236": 945, "237": 971}}, "total_num_arrival": 5282, "not_served": 2252}